COPYING
MANIFEST.in
README.rst
setup.py
bin/kp
keepassx/__init__.py
keepassx/clipboard.py
keepassx/db.py
keepassx/main.py
keepassx.egg-info/PKG-INFO
keepassx.egg-info/SOURCES.txt
keepassx.egg-info/dependency_links.txt
keepassx.egg-info/requires.txt
keepassx.egg-info/top_level.txt