Metadata-Version: 1.0
Name: keepassx
Version: 0.0.1
Summary: Python API and CLI for KeePassX
Home-page: https://github.com/jamesls/python-keepassx
Author: James Saryerwinnie
Author-email: js@jamesls.com
License: UNKNOWN
Keywords: keepassx
Platform: UNKNOWN
Classifier: Development Status :: 3 - Alpha
Classifier: License :: OSI Approved :: GNU General Public License v2 or later (GPLv2+)
Classifier: Programming Language :: Python :: 2.7
Classifier: Programming Language :: Python :: 3.3
